mcp_jamie_params/__init__.py
mcp_jamie_params/server.py
mcp_jamie_params-1.0.8.dist-info/METADATA
mcp_jamie_params-1.0.8.dist-info/WHEEL
mcp_jamie_params-1.0.8.dist-info/entry_points.txt
mcp_jamie_params-1.0.8.dist-info/RECORD
